coldsweat/__init__.py
coldsweat/commands.py
coldsweat/feed.py
coldsweat/fetcher.py
coldsweat/filters.py
coldsweat/markup.py
coldsweat/models.py
coldsweat/utilities.py
coldsweat/auth/__init__.py
coldsweat/auth/routes.py
coldsweat/fever/__init__.py
coldsweat/fever/routes.py
coldsweat/main/__init__.py
coldsweat/main/routes.py
coldsweat/static/all.css
coldsweat/static/all.css.map
coldsweat/static/app.js
coldsweat/static/app.js.map
coldsweat/static/favicon.ico
coldsweat/static/favicon.png
coldsweat/static/fontawesome-webfont.0e69da3d.eot
coldsweat/static/fontawesome-webfont.3b8a7ff6.eot
coldsweat/static/fontawesome-webfont.562db103.svg
coldsweat/static/fontawesome-webfont.87519f92.woff
coldsweat/static/fontawesome-webfont.aed764d9.eot
coldsweat/static/fontawesome-webfont.c57f9fe9.woff
coldsweat/static/fontawesome-webfont.eca4f89d.ttf
coldsweat/static/fontawesome-webfont.fa9c43e0.ttf
coldsweat/static/fontawesome-webfont.fbd6655f.svg
coldsweat/static/star-fill.3deaafe5.svg
coldsweat/static/star-fill.7474098e.svg
coldsweat/static/star.7834d1b0.svg
coldsweat/static/star.7906531e.svg
coldsweat/static/images/apple-touch-icon.png
coldsweat/static/images/larr.png
coldsweat/static/images/nav-rarr.png
coldsweat/static/images/rarr.png
coldsweat/static/images/tile-icon.png
coldsweat/static/javascripts/app.js
coldsweat/static/javascripts/plugins.js
coldsweat/static/javascripts/vendor/bootstrap-min.js
coldsweat/static/javascripts/vendor/head.load.min.js
coldsweat/static/javascripts/vendor/jquery-min.js
coldsweat/static/javascripts/vendor/modernizr-min.js
coldsweat/static/javascripts/vendor/bootstrap/bootstrap-affix.js
coldsweat/static/javascripts/vendor/bootstrap/bootstrap-alert.js
coldsweat/static/javascripts/vendor/bootstrap/bootstrap-button.js
coldsweat/static/javascripts/vendor/bootstrap/bootstrap-carousel.js
coldsweat/static/javascripts/vendor/bootstrap/bootstrap-collapse.js
coldsweat/static/javascripts/vendor/bootstrap/bootstrap-dropdown.js
coldsweat-0.10.2.dist-info/LICENSE
coldsweat-0.10.2.dist-info/METADATA
coldsweat-0.10.2.dist-info/WHEEL
coldsweat-0.10.2.dist-info/entry_points.txt
coldsweat-0.10.2.dist-info/top_level.txt
coldsweat-0.10.2.dist-info/RECORD
