Metadata-Version: 2.1
Name: coldsweat
Version: 0.10.2
Summary: Web RSS aggregator and reader compatible with the Fever API
Author: Andrea Peltrin
Project-URL: Homepage, https://github.com/passiomatic/coldsweat
Project-URL: Bug Tracker, https://github.com/passiomatic/coldsweat/issues
Classifier: Programming Language :: Python :: 3
Classifier: License :: OSI Approved :: BSD License
Classifier: Operating System :: OS Independent
Classifier: Development Status :: 3 - Alpha
Classifier: Environment :: Console
Classifier: Environment :: Web Environment
Classifier: Framework :: Flask
Requires-Python: >=3.9
License-File: LICENSE
Requires-Dist: peewee <4,>=3.15.4
Requires-Dist: urllib3 <2
Requires-Dist: requests <3,>=2.28.1
Requires-Dist: feedparser >=6.0.10
Requires-Dist: flask <3.1,>=3.0.0
Requires-Dist: flask-login >=0.6.3
Requires-Dist: flask-cdn >=1.5.3
Requires-Dist: tomli <3,>=2.0.1
Requires-Dist: markupsafe <3,>=2.1
